RFIDFrame/RFID.py
RFIDFrame/__init__.py
RFIDFrame-0.0.1.dist-info/LICENSE
RFIDFrame-0.0.1.dist-info/METADATA
RFIDFrame-0.0.1.dist-info/WHEEL
RFIDFrame-0.0.1.dist-info/top_level.txt
RFIDFrame-0.0.1.dist-info/RECORD
