Metadata-Version: 2.1
Name: RFIDFrame
Version: 0.0.1
Summary: A Framework for MFRC522 RFID Devices in Python
Home-page: https://github.com/vproHacks/RFIDFrame
Author: Vraj Prajapati
Author-email: blahthing8@gmail.com
License: UNKNOWN
Platform: UNKNOWN
Classifier: Programming Language :: Python :: 3
Classifier: License :: OSI Approved :: MIT License
Classifier: Operating System :: OS Independent
